autoFRK/__init__.py
autoFRK/autoFRK.py
autoFRK/mrts.py
autoFRK/utils/LK_object.py
autoFRK/utils/__init__.py
autoFRK/utils/device.py
autoFRK/utils/estimator.py
autoFRK/utils/helper.py
autoFRK/utils/logger.py
autoFRK/utils/matrix_operator.py
autoFRK/utils/predictor.py
autoFRK/utils/utils.py
autofrk-1.2.3.dist-info/licenses/LICENSE
autofrk-1.2.3.dist-info/METADATA
autofrk-1.2.3.dist-info/WHEEL
autofrk-1.2.3.dist-info/top_level.txt
autofrk-1.2.3.dist-info/RECORD
