Metadata-Version: 2.4
Name: autoFRK
Version: 1.2.3
Summary: autoFRK: Automatic Fixed Rank Kriging. The Python version with PyTorch
Author: ShengLi Tzeng, Hsin-Cheng Huang, Wen-Ting Wang, Yao-Chih Hsu
Maintainer: Yao-Chih Hsu
License-Expression: GPL-3.0-or-later
Project-URL: Homepage, https://github.com/Josh-test-lab/autoFRK-python
Project-URL: Issues, https://github.com/Josh-test-lab/autoFRK-python/issues
Keywords: kriging,spatial statistics,torch,autoFRK,geostatistics
Classifier: Development Status :: 5 - Production/Stable
Classifier: Intended Audience :: Science/Research
Classifier: Topic :: Scientific/Engineering :: Artificial Intelligence
Classifier: Programming Language :: Python :: 3
Classifier: Programming Language :: Python :: 3.10
Classifier: Programming Language :: Python :: 3.11
Classifier: Programming Language :: Python :: 3.12
Requires-Python: >=3.10
License-File: LICENSE
Requires-Dist: numpy>=1.23
Requires-Dist: pandas>=1.6
Requires-Dist: torch>=2.1
Requires-Dist: scipy>=1.10
Requires-Dist: colorlog>=6.7
Dynamic: license-file
